nucleus_api/__init__.py
nucleus_api/api_client.py
nucleus_api/auth_api.py
nucleus_api/configuration.py
nucleus_api/environment.py
nucleus_api/rest.py
nucleus_api/api/__init__.py
nucleus_api/api/account_api.py
nucleus_api/api/admin_client_api.py
nucleus_api/api/aggregation_account_api.py
nucleus_api/api/allocation_api.py
nucleus_api/api/benchmark_api.py
nucleus_api/api/budget_api.py
nucleus_api/api/bulk_api.py
nucleus_api/api/business_api.py
nucleus_api/api/card_api.py
nucleus_api/api/client_api.py
nucleus_api/api/contact_api.py
nucleus_api/api/decision_tree_api.py
nucleus_api/api/document_api.py
nucleus_api/api/financial_statement_api.py
nucleus_api/api/funding_api.py
nucleus_api/api/goal_api.py
nucleus_api/api/household_api.py
nucleus_api/api/invoice_api.py
nucleus_api/api/model_api.py
nucleus_api/api/order_api.py
nucleus_api/api/overflow_api.py
nucleus_api/api/portfolio_api.py
nucleus_api/api/questionnaire_api.py
nucleus_api/api/resource_api.py
nucleus_api/api/risk_profile_api.py
nucleus_api/api/roundup_api.py
nucleus_api/api/score_api.py
nucleus_api/api/securities_api.py
nucleus_api/api/spending_control_api.py
nucleus_api/api/utils_api.py
nucleus_api/api/webhook_api.py
nucleus_api/models/__init__.py
nucleus_api/models/account.py
nucleus_api/models/account_allocation_mapping.py
nucleus_api/models/account_map.py
nucleus_api/models/account_permission_vo.py
nucleus_api/models/account_portfolio_rebalance_request.py
nucleus_api/models/account_status.py
nucleus_api/models/account_type.py
nucleus_api/models/acl_client_permission_vo.py
nucleus_api/models/admin_client.py
nucleus_api/models/aggregation_account.py
nucleus_api/models/aggregation_account_balance.py
nucleus_api/models/aggregation_account_holding.py
nucleus_api/models/aggregation_account_transaction.py
nucleus_api/models/aggregation_accounts_map.py
nucleus_api/models/allocation.py
nucleus_api/models/allocation_aggregated_vo.py
nucleus_api/models/allocation_composition.py
hydrogen_nucleus_api-1.9.4.dist-info/METADATA
hydrogen_nucleus_api-1.9.4.dist-info/WHEEL
hydrogen_nucleus_api-1.9.4.dist-info/top_level.txt
hydrogen_nucleus_api-1.9.4.dist-info/RECORD
