Metadata-Version: 2.1
Name: hydrogen-nucleus-api
Version: 1.9.4
Summary: Hydrogen Nucleus API
Home-page: https://www.hydrogenplatform.com
Author-email: info@hydrogenplatform.com
License: UNKNOWN
Keywords: Swagger,Hydrogen Nucleus API
Platform: UNKNOWN
Requires-Dist: certifi (>=2017.4.17)
Requires-Dist: python-dateutil (>=2.1)
Requires-Dist: six (>=1.10)
Requires-Dist: urllib3 (>=1.23)
